luqui/cli.py
luqui/luqui.py
luqui/testing.ipynb
luqui-0.1.1.3.dist-info/entry_points.txt
luqui-0.1.1.3.dist-info/LICENSE
luqui-0.1.1.3.dist-info/WHEEL
luqui-0.1.1.3.dist-info/METADATA
luqui-0.1.1.3.dist-info/RECORD
