Metadata-Version: 2.1
Name: luqui
Version: 0.1.1.3
Summary: 
Author: pgbarletta
Author-email: pbarletta@gmail.com
Requires-Python: >=3.8,<3.11
Classifier: Programming Language :: Python :: 3
Classifier: Programming Language :: Python :: 3.10
Classifier: Programming Language :: Python :: 3.8
Classifier: Programming Language :: Python :: 3.9
Requires-Dist: GromacsWrapper (>=0.8.1,<0.9.0)
Requires-Dist: attrs (>=21.4.0,<22.0.0)
Requires-Dist: pdb2pqr (>=3.5.0,<4.0.0)
Requires-Dist: scipy (>=1.7,<2.0)
Requires-Dist: toml (>=0.10.1,<0.11.0)
